LICENSE.txt
MANIFEST.in
setup.py
bashpunchcard/__init__.py
bashpunchcard.egg-info/PKG-INFO
bashpunchcard.egg-info/SOURCES.txt
bashpunchcard.egg-info/dependency_links.txt
bashpunchcard.egg-info/entry_points.txt
bashpunchcard.egg-info/requires.txt
bashpunchcard.egg-info/top_level.txt
bashpunchcard.egg-info/zip-safe