Metadata-Version: 1.1
Name: bashpunchcard
Version: 0.1.1
Summary: Command line script for creating a PNG punchcard graph of your bash history
Home-page: https://github.com/askedrelic/bash-history-punchcard
Author: Matt Behrens
Author-email: askedrelic@gmail.com
License: The MIT License (MIT)
